setup.py
wyjtools/__init__.py
wyjtools.egg-info/PKG-INFO
wyjtools.egg-info/SOURCES.txt
wyjtools.egg-info/dependency_links.txt
wyjtools.egg-info/top_level.txt