Metadata-Version: 2.1
Name: wyjtools
Version: 0.0.1
Summary: a library to grap all the useful tools
Home-page: UNKNOWN
Author: Yujue Wang
Author-email: spsc83@gmail.com
License: MIT License
Keywords: tools
Platform: any
